pyfile_runner/__init__.py
pyfile_runner/runner/__init__.py
pyfile_runner/runner/event.py
pyfile_runner/runner/runner.py
pyfile_runner/runner/util.py
pyfile_runner/runner/worker.py
pyfile_runner/ui/__init__.py
pyfile_runner/ui/app.py
pyfile_runner/ui/app.tcss
pyfile_runner/ui/messages.py
pyfile_runner/ui/components/__init__.py
pyfile_runner/ui/components/files_bar.py
pyfile_runner/ui/components/files_progress.py
pyfile_runner/ui/components/files_tree.py
pyfile_runner/ui/components/output_viewer.py
pyfile_runner/ui/components/stderr_viewer.py
pyfile_runner/ui/components/stdout_viewer.py
pyfile_runner-0.1.4.dist-info/METADATA
pyfile_runner-0.1.4.dist-info/WHEEL
pyfile_runner-0.1.4.dist-info/RECORD
